like_laravel_db/__init__.py
like_laravel_db/config.py
like_laravel_db/db.py
like_laravel_db/mysql_comm.py
like_laravel_db/utils.py
tests/__init__.py
tests/db_test.py
like_laravel_db-0.1.1.dist-info/LICENSE
like_laravel_db-0.1.1.dist-info/METADATA
like_laravel_db-0.1.1.dist-info/WHEEL
like_laravel_db-0.1.1.dist-info/top_level.txt
like_laravel_db-0.1.1.dist-info/RECORD
