Metadata-Version: 2.1
Name: like_laravel_db
Version: 0.1.1
Summary: python like laravel db
Home-page: https://gitee.com/tbf1211/like-laravel-db
Author: TeaTang
Author-email: 534427931@qq.com
License: Apache-2.0 license
Project-URL: Bug Tracker, https://gitee.com/tbf1211/like-laravel-db/issues
Project-URL: Documentation, https://gitee.com/tbf1211/like-laravel-db
Project-URL: Source Code, https://gitee.com/tbf1211/like-laravel-db
Platform: any
Requires-Python: >=3.6
License-File: LICENSE
Requires-Dist: DBUtils
Requires-Dist: PyMySQL
